gotthard/__init__.py
gotthard/__main__.py
gotthard/cli.py
gotthard-1.11.dist-info/DESCRIPTION.rst
gotthard-1.11.dist-info/METADATA
gotthard-1.11.dist-info/RECORD
gotthard-1.11.dist-info/WHEEL
gotthard-1.11.dist-info/entry_points.txt
gotthard-1.11.dist-info/metadata.json
gotthard-1.11.dist-info/top_level.txt
